xvideos_dl/__init__.py
xvideos_dl/__main__.py
xvideos_dl/constant.py
xvideos_dl/py.typed
xvideos_dl/xvideos_dl.py
xvideos_dl-1.3.0.dist-info/entry_points.txt
xvideos_dl-1.3.0.dist-info/LICENSE
xvideos_dl-1.3.0.dist-info/WHEEL
xvideos_dl-1.3.0.dist-info/METADATA
xvideos_dl-1.3.0.dist-info/RECORD
