Metadata-Version: 2.1
Name: xvideos-dl
Version: 1.3.0
Summary: CLI to download videos from https://xvideos.com
Home-page: https://github.com/lonsty/xvideos-dl
License: MIT
Keywords: xvideos,downloader,videos
Author: xvideos-dl
Author-email: lonsty@sina.com
Requires-Python: >=3.6.1,<4.0.0
Classifier: Development Status :: 3 - Alpha
Classifier: Intended Audience :: Developers
Classifier: License :: OSI Approved :: MIT License
Classifier: Operating System :: OS Independent
Classifier: Programming Language :: Python :: 3
Classifier: Programming Language :: Python :: 3.10
Classifier: Programming Language :: Python :: 3.7
Classifier: Programming Language :: Python :: 3.8
Classifier: Programming Language :: Python :: 3.9
Classifier: Topic :: Software Development :: Libraries :: Python Modules
Requires-Dist: beautifulsoup4 (>=4.9.0,<5.0.0)
Requires-Dist: cursor (>=1.3.4,<2.0.0)
Requires-Dist: ffmpeg-python (>=0.2.0,<0.3.0)
Requires-Dist: importlib_metadata (>=1.6,<4.0); python_version < "3.8"
Requires-Dist: integv (>=1.3.0,<2.0.0)
Requires-Dist: requests (>=2.25.0,<3.0.0)
Requires-Dist: rich (>=10.0.0,<11.0.0)
Requires-Dist: typer[all] (>=0.3.2,<0.4.0)
Project-URL: Repository, https://github.com/lonsty/xvideos-dl
